ape_anthropic/__init__.py
ape_anthropic/executor.py
ape_anthropic/generator.py
ape_anthropic/schema.py
ape_anthropic/utils.py
ape_anthropic-1.0.5.dist-info/licenses/LICENSE
ape_anthropic-1.0.5.dist-info/METADATA
ape_anthropic-1.0.5.dist-info/WHEEL
ape_anthropic-1.0.5.dist-info/top_level.txt
ape_anthropic-1.0.5.dist-info/RECORD
