Metadata-Version: 2.4
Name: ape-anthropic
Version: 1.0.5
Summary: Anthropic Claude integration for APE (AI Programmatic Execution)
Author-email: David Van Aelst <david@skyrah.be>
License: MIT
Project-URL: Homepage, https://github.com/yourusername/ape-anthropic
Project-URL: Documentation, https://github.com/yourusername/ape-anthropic/blob/main/README.md
Project-URL: Repository, https://github.com/yourusername/ape-anthropic
Classifier: Development Status :: 3 - Alpha
Classifier: Intended Audience :: Developers
Classifier: License :: OSI Approved :: MIT License
Classifier: Programming Language :: Python :: 3.11
Classifier: Topic :: Software Development :: Libraries
Requires-Python: >=3.11
License-File: LICENSE
Requires-Dist: ape-lang>=1.0.4
Requires-Dist: typing-extensions>=4.0.0
Provides-Extra: anthropic
Requires-Dist: anthropic>=0.18.0; extra == "anthropic"
Provides-Extra: dev
Requires-Dist: pytest>=7.0.0; extra == "dev"
Requires-Dist: pytest-cov>=4.0.0; extra == "dev"
Requires-Dist: black>=23.0.0; extra == "dev"
Requires-Dist: mypy>=1.0.0; extra == "dev"
Dynamic: license-file
